json_to_swagger/__init__.py
json_to_swagger/converter.py
json_to_swagger-0.0.5.dist-info/LICENSE
json_to_swagger-0.0.5.dist-info/METADATA
json_to_swagger-0.0.5.dist-info/WHEEL
json_to_swagger-0.0.5.dist-info/top_level.txt
json_to_swagger-0.0.5.dist-info/RECORD
