Metadata-Version: 2.1
Name: json-to-swagger
Version: 0.0.5
Summary: Python utility created to convert JSON to Swagger definitions structure, based on entities concept.
Home-page: https://github.com/armandoalmeida/json-to-swagger
Author: Jose Armando Almeida Neto
Author-email: jose@armandoalmeida.com.br
License: UNKNOWN
Platform: UNKNOWN
Classifier: Programming Language :: Python :: 3
Classifier: License :: OSI Approved :: GNU General Public License (GPL)
Classifier: Operating System :: OS Independent
Requires-Python: >=3.6
Requires-Dist: swagger-parser
Requires-Dist: pyyaml
Requires-Dist: inflect
